{
  "tables": [
    {
      "table": "delivery_routes",
      "total": 34,
      "clientAccesses": 6,
      "adminAccesses": 0,
      "operations": [
        "UNKNOWN",
        "SELECT"
      ],
      "files": [
        "app/actions/logistics/create-route.ts",
        "app/api/debug-planning/route.ts",
        "app/api/expedition/finish-return/route.ts",
        "app/api/expedition/partial-load/route.ts",
        "app/api/expedition/start-route/route.ts",
        "app/api/logistics/routes/[routeId]/process-return/route.ts",
        "app/api/sales/orders/[id]/route.ts",
        "app/api/test/setup-delivery-test/route.ts",
        "inspect_route.ts",
        "lib/data/expedition.ts",
        "scripts/debug_planning.ts",
        "scripts/fix_company_mismatch.ts",
        "scripts/fix_unscheduled_routes.ts"
      ]
    },
    {
      "table": "company_settings",
      "total": 30,
      "clientAccesses": 5,
      "adminAccesses": 4,
      "operations": [
        "UNKNOWN",
        "SELECT",
        "INSERT",
        "DELETE"
      ],
      "files": [
        "app/api/company/cert-a1/delete/route.ts",
        "app/api/company/cert-a1/password/route.ts",
        "app/api/company/cert-a1/upload/route.ts",
        "app/api/company/logo/delete/route.ts",
        "app/api/company/logo/signed-url/route.ts",
        "app/api/company/logo/upload/route.ts",
        "app/api/test/setup-delivery-test/route.ts",
        "app/app/fiscal/operacoes/page.tsx",
        "components/fiscal/FiscalOperationForm.tsx",
        "components/sales/TabGeneral.tsx",
        "components/sales/order/SalesOrderForm.tsx",
        "components/settings/NumberingAdjustmentModal.tsx",
        "lib/data/company-settings.ts",
        "lib/fiscal/nfe/offline/emitOffline.ts",
        "lib/hooks/useDeliveriesModel.ts",
        "lib/nfe/sefaz/services/certificateLoader.ts",
        "scripts/check-martigran.ts",
        "scripts/fix-duplicate-companies.ts",
        "scripts/inspect-companies.ts"
      ]
    },
    {
      "table": "sales_documents",
      "total": 78,
      "clientAccesses": 17,
      "adminAccesses": 2,
      "operations": [
        "SELECT",
        "UNKNOWN",
        "UPDATE",
        "INSERT",
        "DELETE"
      ],
      "files": [
        "app/api/debug/order-status/route.ts",
        "app/api/expedition/finish-return/route.ts",
        "app/api/expedition/partial-load/route.ts",
        "app/api/expedition/start-route/route.ts",
        "app/api/logistics/routes/[routeId]/process-return/route.ts",
        "app/api/sales/approve-batch/route.ts",
        "app/api/sales/delete-batch/route.ts",
        "app/api/sales/orders/[id]/route.ts",
        "app/api/sales/print-batch/route.ts",
        "app/api/test/seed-sales-order/route.ts",
        "check_draft_number.ts",
        "check_id.ts",
        "check_order_48.ts",
        "check_order_51.ts",
        "check_order_64.ts",
        "check_order_67.ts",
        "components/fiscal/InvoiceModal.tsx",
        "components/sales/order/SalesOrderForm.tsx",
        "debug_order_70.ts",
        "lib/data/expedition.ts",
        "lib/data/sales-orders.ts",
        "lib/fiscal/nfe/offline/emitOffline.ts",
        "lib/fiscal/nfe-actions.ts",
        "lib/fiscal/nfe-emission-actions.ts",
        "lib/pcp/planning-service.ts",
        "scripts/check-martigran.ts",
        "scripts/fix_company_mismatch.ts",
        "scripts/inspect-order.ts",
        "scripts/nfe-offline-sign.ts"
      ]
    },
    {
      "table": "delivery_route_orders",
      "total": 41,
      "clientAccesses": 10,
      "adminAccesses": 0,
      "operations": [
        "UNKNOWN",
        "DELETE",
        "SELECT",
        "INSERT"
      ],
      "files": [
        "app/api/debug/order-status/route.ts",
        "app/api/debug-planning/route.ts",
        "app/api/expedition/finish-return/route.ts",
        "app/api/expedition/start-route/route.ts",
        "app/api/logistics/routes/[routeId]/occurrences/route.ts",
        "app/api/logistics/routes/[routeId]/process-return/route.ts",
        "app/api/sales/approve-batch/route.ts",
        "app/api/sales/orders/[id]/route.ts",
        "app/api/test/setup-delivery-test/route.ts",
        "check_constraint.ts",
        "check_duplicates.ts",
        "check_id.ts",
        "components/expedicao/LoadingChecklist.tsx",
        "debug_order_70.ts",
        "inspect_route.ts",
        "lib/data/expedition.ts",
        "lib/data/sales-orders.ts",
        "lib/pcp/planning-service.ts",
        "scripts/check_columns.ts",
        "scripts/debug_planning.ts",
        "scripts/fix_company_mismatch.ts"
      ]
    },
    {
      "table": "sales_document_items",
      "total": 19,
      "clientAccesses": 0,
      "adminAccesses": 0,
      "operations": [
        "UNKNOWN",
        "SELECT",
        "DELETE",
        "UPDATE",
        "INSERT"
      ],
      "files": [
        "app/api/expedition/finish-return/route.ts",
        "app/api/expedition/partial-load/route.ts",
        "app/api/logistics/routes/[routeId]/process-return/route.ts",
        "app/api/sales/orders/[id]/route.ts",
        "app/api/test/seed-sales-order/route.ts",
        "components/expedition/OrderItemsPopover.tsx",
        "components/sales/order/SalesOrderForm.tsx",
        "lib/data/sales-orders.ts",
        "lib/services/deliveries.ts"
      ]
    },
    {
      "table": "items",
      "total": 68,
      "clientAccesses": 18,
      "adminAccesses": 0,
      "operations": [
        "SELECT",
        "UNKNOWN",
        "UPDATE",
        "INSERT"
      ],
      "files": [
        "app/api/logistics/routes/[routeId]/process-return/route.ts",
        "app/api/test/seed-sales-order/route.ts",
        "app/app/cadastros/produtos/[id]/page.tsx",
        "app/app/cadastros/produtos/page.tsx",
        "app/app/estoque/page.tsx",
        "check_items_columns.ts",
        "compare_wo_ui_vs_db.ts",
        "components/app/ProductSelector.tsx",
        "components/inventory/InventoryMovementModal.tsx",
        "components/pcp/NewWorkOrderModal.tsx",
        "components/products/ProductForm.tsx",
        "components/purchases/PurchaseOrderForm.tsx",
        "components/purchases/PurchaseOrderModal.tsx",
        "components/purchases/QuickEntryModal.tsx",
        "debug_all_wos_aveia.ts",
        "debug_bom_aveia_all.ts",
        "debug_bom_structure.ts",
        "debug_po_unit_cost.ts",
        "debug_purchase_needs_aveia.ts",
        "debug_reverse_engineer.ts",
        "debug_wo_direct.ts",
        "debug_wo_service_role.ts",
        "find_missing_consumption.ts",
        "lib/data/items.ts",
        "lib/data/uoms.ts",
        "lib/price-tables.ts",
        "lib/purchases/needs-service.ts",
        "lib/purchases/purchases-db.ts",
        "scripts/check_all_weights.ts",
        "scripts/check_bom_lines_constraint.ts",
        "scripts/check_granola.ts",
        "scripts/check_inv_details.ts",
        "scripts/check_items_cols.ts",
        "scripts/check_purchase_profile.ts",
        "scripts/check_purchase_profile_cols.ts",
        "scripts/check_queries.ts",
        "scripts/fix_existing_costs_conversion.ts",
        "scripts/force_fix_aveia_cost.ts",
        "scripts/recalculate_all_costs.ts",
        "scripts/test_cost_functions.ts",
        "scripts/test_costing_system.ts"
      ]
    },
    {
      "table": "price_tables",
      "total": 7,
      "clientAccesses": 0,
      "adminAccesses": 0,
      "operations": [
        "SELECT",
        "UNKNOWN"
      ],
      "files": [
        "components/purchases/PurchaseOrderForm.tsx",
        "components/sales/order/SalesOrderForm.tsx",
        "lib/clients-db.ts",
        "lib/price-tables.ts"
      ]
    },
    {
      "table": "price_table_items",
      "total": 3,
      "clientAccesses": 0,
      "adminAccesses": 0,
      "operations": [
        "UNKNOWN"
      ],
      "files": [
        "components/sales/order/SalesOrderForm.tsx",
        "lib/price-tables.ts"
      ]
    },
    {
      "table": "users",
      "total": 5,
      "clientAccesses": 0,
      "adminAccesses": 0,
      "operations": [
        "SELECT",
        "UNKNOWN"
      ],
      "files": [
        "components/sales/order/SalesOrderForm.tsx",
        "node_modules_DELETE_ME/@supabase/postgrest-js/src/PostgrestBuilder.ts",
        "node_modules_DELETE_ME/@supabase/postgrest-js/src/PostgrestQueryBuilder.ts"
      ]
    }
  ]
}